seeq/addons/constraintdetection/_SPy_functions.py
seeq/addons/constraintdetection/__init__.py
seeq/addons/constraintdetection/__main__.py
seeq/addons/constraintdetection/_copy.py
seeq/addons/constraintdetection/_saturation_detection.py
seeq/addons/constraintdetection/_seeq_add_on.py
seeq/addons/constraintdetection/_version.py
seeq/addons/constraintdetection/deployment_notebook/constraint_detection_master.ipynb
seeq/addons/constraintdetection/deployment_notebook/thresholds.PNG
seeq/addons/constraintdetection/utils/__init__.py
seeq/addons/constraintdetection/utils/_common.py
seeq/addons/constraintdetection/utils/_permissions.py
seeq/addons/constraintdetection/utils/_sdl.py
seeq_constraintdetection-0.0.41.dist-info/LICENSE
seeq_constraintdetection-0.0.41.dist-info/METADATA
seeq_constraintdetection-0.0.41.dist-info/NOTICE
seeq_constraintdetection-0.0.41.dist-info/WHEEL
seeq_constraintdetection-0.0.41.dist-info/top_level.txt
seeq_constraintdetection-0.0.41.dist-info/RECORD
