Metadata-Version: 2.1
Name: seeq-constraintdetection
Version: 0.0.41
Summary: Constraint and saturation detection in control loop data in Seeq
Home-page: https://github.com/HAW-Process-Automation/Constraint-Detection
Author: Lea Tiedemann
Author-email: lea.tiedemann@seeq.com
License: Apache License 2.0
Platform: Linux
Platform: Windows
Classifier: Programming Language :: Python :: 3.7
Classifier: Operating System :: OS Independent
Requires-Python: >=3.7
License-File: LICENSE
License-File: NOTICE
Requires-Dist: ipyvuetify (>=1.8.2)
Requires-Dist: numpy (>=1.20.1)
Requires-Dist: pandas (>=1.2.4)
Requires-Dist: pytz (~=2021.1)
